alibabacloud_resourcemanager20161111/__init__.py
alibabacloud_resourcemanager20161111/client.py
alibabacloud_resourcemanager20161111/models.py
alibabacloud_resourcemanager20161111-1.0.1.dist-info/LICENSE
alibabacloud_resourcemanager20161111-1.0.1.dist-info/METADATA
alibabacloud_resourcemanager20161111-1.0.1.dist-info/WHEEL
alibabacloud_resourcemanager20161111-1.0.1.dist-info/top_level.txt
alibabacloud_resourcemanager20161111-1.0.1.dist-info/RECORD
